Metadata-Version: 1.0
Name: tello-lazer
Version: 1.0
Summary: Tello Edu Extention KIT controller
Home-page: UNKNOWN
Author: UNKNOWN
Author-email: dimitriz@mail.ru
License: UNKNOWN
Platform: UNKNOWN
